idf_tags-0.1.1.dist-info/METADATA
idf_tags-0.1.1.dist-info/RECORD
idf_tags-0.1.1.dist-info/WHEEL
idf_tags-0.1.1.dist-info/entry_points.txt
idf_tags-0.1.1.dist-info/top_level.txt
idftags/__init__.py
idftags/cli.py
idftags/idf_tag.py
