Metadata-Version: 2.1
Name: idf-tags
Version: 0.1.1
Summary: A ViM-usable tags file generator for EnergyPlus IDF files.
Home-page: https://github.com/jmarrec/idf-tags
Author: Julien Marrec
Author-email: julien@effibem.com
License: MIT
Keywords: energyplus,tags,vim,vi,cli
Platform: UNKNOWN
Classifier: Intended Audience :: Science/Research
Classifier: Topic :: Scientific/Engineering
Classifier: License :: OSI Approved :: MIT License
Classifier: Natural Language :: English
Classifier: Operating System :: OS Independent
Classifier: Programming Language :: Python :: 2
Classifier: Programming Language :: Python :: 2.6
Classifier: Programming Language :: Python :: 2.7
Classifier: Programming Language :: Python :: 3
Classifier: Programming Language :: Python :: 3.2
Classifier: Programming Language :: Python :: 3.3
Classifier: Programming Language :: Python :: 3.4
Provides-Extra: test
Requires-Dist: eppy
Requires-Dist: docopt
Provides-Extra: test
Requires-Dist: coverage; extra == 'test'
Requires-Dist: pytest; extra == 'test'
Requires-Dist: pytest-cov; extra == 'test'
Requires-Dist: pytest-pep8; extra == 'test'
Requires-Dist: tox; extra == 'test'
